tarotteller/__init__.py
tarotteller/core/__init__.py
tarotteller/core/context.py
tarotteller/core/correspondences.py
tarotteller/core/data.py
tarotteller/core/deck.py
tarotteller/core/engine.py
tarotteller/core/knowledge.py
tarotteller/core/spreads.py
tarotteller/interfaces/__init__.py
tarotteller/interfaces/cli.py
tarotteller/interfaces/gui.py
tarotteller/narrative/__init__.py
tarotteller/narrative/immersive.py
tarotteller-0.2.0.dist-info/METADATA
tarotteller-0.2.0.dist-info/WHEEL
tarotteller-0.2.0.dist-info/entry_points.txt
tarotteller-0.2.0.dist-info/top_level.txt
tarotteller-0.2.0.dist-info/RECORD
