Metadata-Version: 2.4
Name: tarotteller
Version: 0.2.0
Summary: A feature-rich tarot reading toolkit with graphical and CLI interfaces.
Author: Tarot Teller Maintainers
License: MIT
Requires-Python: >=3.9
